
{
    "timeline":
    {
        "headline":"Jesse Gangi",
        "type":"default",
        "startDate":"1999,1",
        "text":"<i><span class='c1'>My Online Resume</span> & <span class='c2'>Contact</span></i>",
        "asset":
        {
            "media":"assets/img/notes.png",
            "credit":"<a href='http://jessegangi.com/'>LINK</a>",
            "caption":""
        },
        "date": [
            {
                "startDate":"1999,5,1",
				"endDate":"2001,5,1",
                "headline":"Past Employment: <br />FuncoLand",
                "text":"FuncoLand.",
                "asset":
                {
                    "media":"assets/img/notes.png",
                    "credit":"<a href='http://jessegangi.com/past/employment/funcoland/'>FuncoLand</a>",
                    "caption":"Now GameStop"
                }
            },
            {
                "startDate":"2009,5",
                "headline":"Redesign of my portfolio",
                "text":"",
                "asset":
                {
                    "media":"assets/img/shots/sidebar_s3.jpg",
                    "credit":"<a href='http://dribbble.com/shots/401334-Sidebar'>by Chris Brauckmuller</a>",
                    "caption":""
                }
            },
            {
                "startDate":"2009,7",
                "headline":"Another time-lapse experiment",
                "text":"",
                "asset":
                {
                    "media":"http://vimeo.com/23237102",
                    "credit":"",
                    "caption":""
                }
            },
            {
                "startDate":"2009,10",
                "headline":"Developed a Gmail Client",
                "text":"",
                "asset":
                {
                    "media":"assets/img/shots/shot_1298590416.jpg",
                    "credit":"<a href='http://dribbble.com/shots/120088-Gmail-Pokki-Final-Ui'>by Justalab</a>",
                    "caption":""
                }
            },
            {
                "startDate":"2010,3",
                "headline":"Logo Design for a pet shop",
                "text":"",
                "asset":
                {
                    "media":"assets/img/shots/pet___you.jpg",
                    "credit":"<a href='http://dribbble.com/shots/444003-Pet-You'>by Nikita Lebedev</a>",
                    "caption":""
                }
            },
            {
                "startDate":"2010,4",
                "headline":"Developed an iPad newspaper application",
                "text":"It was a challenge to create both the design and code in a week.",
                "asset":
                {
                    "media":"assets/img/shots/proto_v4_decoupe_2.jpg",
                    "credit":"<a href='http://dribbble.com/shots/228267-Swiss-newspaper-reader-app-for-iPad-UI-UX-iOS'>by Jonathan Moreira</a>",
                    "caption":""
                }
            },
            {
                "startDate":"2010,8",
                "headline":"Illustration for a big client.",
                "text":"",
                "asset":
                {
                    "media":"assets/img/shots/chameleon.jpg",
                    "credit":"<a href='http://dribbble.com/shots/366400-Chameleon'>Chameleon by Mike</a>",
                    "caption":""
                }
            },
            {
                "startDate":"2010,12",
                "headline":"Advert for Volkswagen",
                "text":"Created the website for their new advertising campaign.",
                "asset":
                {
                    "media":"http://www.youtube.com/watch?v=0-9EYFJ4Clo",
                    "credit":"",
                    "caption":""
                }
            }
        ]
    }
}